themail/__init__.py
Themail-0.0.2.dist-info/LICENSE
Themail-0.0.2.dist-info/METADATA
Themail-0.0.2.dist-info/WHEEL
Themail-0.0.2.dist-info/top_level.txt
Themail-0.0.2.dist-info/RECORD
