Metadata-Version: 2.1
Name: Themail
Version: 0.0.2
Summary: Sending email with python fast
Home-page: https://github.com/claudiotorresarbe/Themail
Author: Cláudio Torres Arbe
Author-email: claudiotarbe@gmail.com
License: UNKNOWN
Platform: UNKNOWN
Classifier: Programming Language :: Python :: 3.8
Classifier: License :: OSI Approved :: MIT License
Classifier: Operating System :: OS Independent
Requires-Python: >=3.6
License-File: LICENSE
